{
  "gridSize": 8,
  "grid": [
    ["हे", "#", "स", "#", "सु", "ना", "मी", "#"],
    ["तु", "#", "ब", "बू", "न", "#", "#", "#"],
    ["वा", "च", "क", "#", "ह", "#", "पा", "#"],
    ["द", "#", "#", "स", "रा", "ह", "नी", "य"],
    ["#", "सिं", "गौ", "टी", "#", "#", "#", "#"],
    ["#", "चा", "#", "क", "म", "लि", "नी", "#"],
    ["सा", "ई", "स", "#", "धु", "#", "#", "#"],
    ["र", "#", "च", "#", "र", "ण", "भू", "मि"]
  ],
  "words": [
    {
      "answer": "सुनामी",
      "clue": "समुद्र की विशाल विनाशकारी लहर",
      "row": 0,
      "col": 4,
      "direction": "across",
      "tiles": [
        "क", "ना", "गि", "घू", "चे", "सु", "छा", "जु", "मी", "टो", "ढा", "ती", "पु", "बो", "र", "खा"
      ]
    },
    {
      "answer": "बबून",
      "clue": "लंबी थूथन वाला एक बंदर",
      "row": 1,
      "col": 2,
      "direction": "across",
      "tiles": [
        "की", "बू", "खु", "गो", "घा", "ब", "चि", "छू", "जे", "न", "ठि", "डू", "ते", "थो", "दि", "यु"
      ]
    },
    {
      "answer": "वाचक",
      "clue": "पढ़कर सुनाने वाला",
      "row": 2,
      "col": 0,
      "direction": "across",
      "tiles": [
        "कू", "च", "खे", "गा", "घि", "वा", "चु", "छे", "क", "जो", "टा", "ठी", "डु", "पे", "फो", "स"
      ]
    },
    {
      "answer": "सराहनीय",
      "clue": "प्रशंसा के योग्य",
      "row": 3,
      "col": 3,
      "direction": "across",
      "tiles": [
        "के", "रा", "खो", "कै", "गी", "स", "घु", "चू", "नी", "छै", "ह", "जि", "टू", "य", "ढे", "तो"
      ]
    },
    {
      "answer": "सिंगौटी",
      "clue": "सिंदूर, कंघी आदि रखने की स्त्रियों की पिटारी",
      "row": 4,
      "col": 1,
      "direction": "across",
      "tiles": [
        "को", "गौ", "खा", "गू", "घे", "सिं", "चो", "छि", "जी", "टी", "टे", "डो", "थी", "दू", "पो", "रु"
      ]
    },
    {
      "answer": "कमलिनी",
      "clue": "छोटा कमल",
      "row": 5,
      "col": 3,
      "direction": "across",
      "tiles": [
        "का", "म", "खि", "गु", "घू", "क", "चे", "लि", "छा", "जु", "नी", "टो", "ढा", "ती", "दे", "भु"
      ]
    },
    {
      "answer": "साईस",
      "clue": "घोड़े की देखभाल करने वाला",
      "row": 6,
      "col": 0,
      "direction": "across",
      "tiles": [
        "कि", "ई", "खी", "गे", "घो", "सा", "चा", "छी", "स", "जे", "ठा", "डि", "ढू", "नो", "यु", "ध"
      ]
    },
    {
      "answer": "रणभूमि",
      "clue": "युद्ध का मैदान",
      "row": 7,
      "col": 4,
      "direction": "across",
      "tiles": [
        "की", "ण", "खु", "गो", "घा", "र", "चि", "छू", "भू", "ठो", "मि", "डा", "दो", "मु", "अ", "य"
      ]
    },
    {
      "answer": "हेतुवाद",
      "clue": "तर्क पर आधारित विचारधारा",
      "row": 0,
      "col": 0,
      "direction": "down",
      "tiles": [
        "कु", "तु", "खू", "का", "घि", "हे", "चु", "छे", "वा", "जो", "द", "टा", "ठी", "डु", "पे", "बो"
      ]
    },
    {
      "answer": "सार",
      "clue": "मुख्य अंश",
      "row": 6,
      "col": 0,
      "direction": "down",
      "tiles": [
        "खो", "र", "री", "घु", "ब", "सा", "चू", "क", "छा", "ड", "य", "जि", "टू", "ढे", "तो", "था"
      ]
    },
    {
      "answer": "सिंचाई",
      "clue": "खेतों में पानी पहुँचाने की प्रक्रिया",
      "row": 4,
      "col": 1,
      "direction": "down",
      "tiles": [
        "त", "चा", "भे", "द", "दू", "सिं", "ला", "खा", "ई", "व", "घे", "ण", "अ", "सु", "म", "ट"
      ]
    },
    {
      "answer": "सबक",
      "clue": "सीख या शिक्षा",
      "row": 0,
      "col": 2,
      "direction": "down",
      "tiles": [
        "त", "ब", "ल", "ह", "गु", "स", "मा", "सि", "क", "चि", "पो", "घू", "न", "चे", "का", "ती"
      ]
    },
    {
      "answer": "सच",
      "clue": "झूठ का विपरीत",
      "row": 6,
      "col": 2,
      "direction": "down",
      "tiles": [
        "कि", "च", "रा", "खी", "गे", "स", "ह", "टी", "पा", "घो", "वि", "श", "हा", "म", "सौ", "ग"
      ]
    },
    {
      "answer": "सटीक",
      "clue": "बिल्कुल सही",
      "row": 3,
      "col": 3,
      "direction": "down",
      "tiles": [
        "खा", "टी", "ज", "सृ", "घा", "स", "र", "बा", "क", "या", "न", "प", "अ", "बू", "इ", "चि"
      ]
    },
    {
      "answer": "सुनहरा",
      "clue": "सोने जैसा रंग वाला",
      "row": 0,
      "col": 4,
      "direction": "down",
      "tiles": [
        "ल", "न", "कु", "ज", "ली", "सु", "श", "य", "ह", "घि", "रा", "ब", "नी", "झि", "पू", "से"
      ]
    },
    {
      "answer": "पानी",
      "clue": "जीवन के लिए आवश्यक तरल",
      "row": 2,
      "col": 6,
      "direction": "down",
      "tiles": [
        "ह", "नी", "र", "जा", "तो", "पा", "था", "द", "न", "स", "डा", "ति", "पु", "भो", "टु", "ल"
      ]
    },
    {
      "answer": "मधुर",
      "clue": "मीठा या सुरीला",
      "row": 5,
      "col": 4,
      "direction": "down",
      "tiles": [
        "ट", "धु", "ख", "रा", "ल", "म", "खा", "व", "र", "गू", "रि", "ना", "इं", "अ", "ती", "या"
      ]
    }
  ]
}